ppdet/__init__.py
ppdet/version.py
ppdet/core/__init__.py
ppdet/core/workspace.py
ppdet/core/config/__init__.py
ppdet/core/config/schema.py
ppdet/core/config/yaml_helpers.py
ppdet/data/__init__.py
ppdet/data/reader.py
ppdet/data/shm_utils.py
ppdet/data/utils.py
ppdet/data/crop_utils/__init__.py
ppdet/data/crop_utils/annotation_cropper.py
ppdet/data/crop_utils/chip_box_utils.py
ppdet/data/source/__init__.py
ppdet/data/source/category.py
ppdet/data/source/coco.py
ppdet/data/source/dataset.py
ppdet/data/source/keypoint_coco.py
ppdet/data/source/mot.py
ppdet/data/source/pose3d_cmb.py
ppdet/data/source/sniper_coco.py
ppdet/data/source/voc.py
ppdet/data/source/widerface.py
ppdet/data/transform/__init__.py
ppdet/data/transform/atss_assigner.py
ppdet/data/transform/autoaugment_utils.py
ppdet/data/transform/batch_operators.py
ppdet/data/transform/gridmask_utils.py
ppdet/data/transform/keypoint_operators.py
ppdet/data/transform/keypoints_3d_operators.py
ppdet/data/transform/mot_operators.py
ppdet/data/transform/op_helper.py
ppdet/data/transform/operators.py
ppdet/data/transform/rotated_operators.py
ppdet/engine/__init__.py
ppdet/engine/callbacks.py
ppdet/engine/env.py
ppdet/engine/export_utils.py
ppdet/engine/tracker.py
ppdet/engine/trainer.py
ppdet/engine/trainer_cot.py
ppdet/engine/trainer_ssod.py
ppdet/metrics/__init__.py
ppdet/metrics/coco_utils.py
ppdet/metrics/json_results.py
ppdet/metrics/keypoint_metrics.py
ppdet/metrics/map_utils.py
ppdet/metrics/mcmot_metrics.py
ppdet/metrics/metrics.py
ppdet/metrics/mot_metrics.py
ppdet/metrics/munkres.py
ppdet/metrics/pose3d_metrics.py
ppdet/metrics/widerface_utils.py
ppdet/model_zoo/MODEL_ZOO
ppdet/model_zoo/__init__.py
ppdet/model_zoo/model_zoo.py
ppdet/model_zoo/tests/__init__.py
ppdet/model_zoo/tests/test_get_model.py
ppdet/model_zoo/tests/test_list_model.py
ppdet/modeling/__init__.py
ppdet/modeling/bbox_utils.py
ppdet/modeling/cls_utils.py
ppdet/modeling/initializer.py
ppdet/modeling/keypoint_utils.py
paddledet-2.6.0.dist-info/LICENSE
paddledet-2.6.0.dist-info/METADATA
paddledet-2.6.0.dist-info/WHEEL
paddledet-2.6.0.dist-info/top_level.txt
paddledet-2.6.0.dist-info/RECORD
